mbzero/__init__.py
mbzero/caarequest.py
mbzero/mbzauth.old.py
mbzero/mbzauth.py
mbzero/mbzerror.py
mbzero/mbzrequest.py
mbzero/oauth2_session_revoke.py
mbzero-0.5.dist-info/licenses/LICENSE
mbzero-0.5.dist-info/METADATA
mbzero-0.5.dist-info/WHEEL
mbzero-0.5.dist-info/top_level.txt
mbzero-0.5.dist-info/RECORD
