Metadata-Version: 2.4
Name: mbzero
Version: 0.5
Summary: Python bindings for the MusicBrainz and the Cover Art Archive webservices
Author-email: Louis Rannou <louson@gresille.org>, Nicolas Mémeint <git@nicomem.com>
Project-URL: Homepage, https://gitlab.com/mbzero/python-mbzero
Classifier: Programming Language :: Python :: 3
Classifier: License :: OSI Approved :: BSD License
Classifier: Operating System :: OS Independent
Classifier: Intended Audience :: Developers
Requires-Python: <4,>=3.8
License-File: LICENSE
Requires-Dist: pytest
Requires-Dist: requests
Requires-Dist: requests_oauthlib
Provides-Extra: lint
Requires-Dist: flake8>=3.5.0; extra == "lint"
Requires-Dist: flake8-simplify; extra == "lint"
Provides-Extra: test
Requires-Dist: pytest>=4.6; extra == "test"
Provides-Extra: cov
Requires-Dist: pytest-cov; extra == "cov"
Provides-Extra: docs
Requires-Dist: sphinx>=7.1.2; extra == "docs"
Requires-Dist: sphinx-rtd-theme>=2.0.0; extra == "docs"
Dynamic: license-file
